structovo/__init__.py
structovo/_enums.py
structovo/_packet.py
structovo/_types.py
structovo-1.0.1.dist-info/LICENSE
structovo-1.0.1.dist-info/METADATA
structovo-1.0.1.dist-info/WHEEL
structovo-1.0.1.dist-info/RECORD
