Metadata-Version: 2.3
Name: structovo
Version: 1.0.1
Summary: A Python library offering a more concise syntax for data packing.
License: MIT
Keywords: serialization,network,packet,struct
Author: GuangChen23333
Author-email: guangchenworks@outlook.com
Requires-Python: >=3.8
Classifier: License :: OSI Approved :: MIT License
Classifier: Programming Language :: Python :: 3
Classifier: Programming Language :: Python :: 3.8
Classifier: Programming Language :: Python :: 3.9
Classifier: Programming Language :: Python :: 3.10
Classifier: Programming Language :: Python :: 3.11
Classifier: Programming Language :: Python :: 3.12
Classifier: Programming Language :: Python :: 3.13
Project-URL: Bug Tracker, https://github.com/GuangChen2333/StructOvO/issues
Project-URL: Repository, https://github.com/GuangChen2333/StructOvO
